setup.py
datuma/__init__.py
datuma/cli.py
datuma/cmd.py
datuma/datuma.py
datuma/version.py
datuma.egg-info/.Python
datuma.egg-info/PKG-INFO
datuma.egg-info/SOURCES.txt
datuma.egg-info/dependency_links.txt
datuma.egg-info/entry_points.txt
datuma.egg-info/requires.txt
datuma.egg-info/top_level.txt
datuma.egg-info/bin/python
datuma.egg-info/bin/python2
datuma.egg-info/bin/python2.7
datuma.egg-info/include/python2.7/Python-ast.h
datuma.egg-info/include/python2.7/Python.h
datuma.egg-info/include/python2.7/abstract.h
datuma.egg-info/include/python2.7/asdl.h
datuma.egg-info/include/python2.7/ast.h
datuma.egg-info/include/python2.7/bitset.h
datuma.egg-info/include/python2.7/boolobject.h
datuma.egg-info/include/python2.7/bufferobject.h
datuma.egg-info/include/python2.7/bytearrayobject.h
datuma.egg-info/include/python2.7/bytes_methods.h
datuma.egg-info/include/python2.7/bytesobject.h
datuma.egg-info/include/python2.7/cStringIO.h
datuma.egg-info/include/python2.7/cellobject.h
datuma.egg-info/include/python2.7/ceval.h
datuma.egg-info/include/python2.7/classobject.h
datuma.egg-info/include/python2.7/cobject.h
datuma.egg-info/include/python2.7/code.h
datuma.egg-info/include/python2.7/codecs.h
datuma.egg-info/include/python2.7/compile.h
datuma.egg-info/include/python2.7/complexobject.h
datuma.egg-info/include/python2.7/datetime.h
datuma.egg-info/include/python2.7/descrobject.h
datuma.egg-info/include/python2.7/dictobject.h
datuma.egg-info/include/python2.7/dtoa.h
datuma.egg-info/include/python2.7/enumobject.h
datuma.egg-info/include/python2.7/errcode.h
datuma.egg-info/include/python2.7/eval.h
datuma.egg-info/include/python2.7/fileobject.h
datuma.egg-info/include/python2.7/floatobject.h
datuma.egg-info/include/python2.7/frameobject.h
datuma.egg-info/include/python2.7/funcobject.h
datuma.egg-info/include/python2.7/genobject.h
datuma.egg-info/include/python2.7/graminit.h
datuma.egg-info/include/python2.7/grammar.h
datuma.egg-info/include/python2.7/import.h
datuma.egg-info/include/python2.7/intobject.h
datuma.egg-info/include/python2.7/intrcheck.h
datuma.egg-info/include/python2.7/iterobject.h
datuma.egg-info/include/python2.7/listobject.h
datuma.egg-info/include/python2.7/longintrepr.h
datuma.egg-info/include/python2.7/longobject.h
datuma.egg-info/include/python2.7/marshal.h
datuma.egg-info/include/python2.7/memoryobject.h
datuma.egg-info/include/python2.7/metagrammar.h
datuma.egg-info/include/python2.7/methodobject.h
datuma.egg-info/include/python2.7/modsupport.h
datuma.egg-info/include/python2.7/moduleobject.h
datuma.egg-info/include/python2.7/node.h
datuma.egg-info/include/python2.7/object.h
datuma.egg-info/include/python2.7/objimpl.h
datuma.egg-info/include/python2.7/opcode.h
datuma.egg-info/include/python2.7/osdefs.h
datuma.egg-info/include/python2.7/parsetok.h
datuma.egg-info/include/python2.7/patchlevel.h
datuma.egg-info/include/python2.7/pgen.h
datuma.egg-info/include/python2.7/pgenheaders.h
datuma.egg-info/include/python2.7/py_curses.h
datuma.egg-info/include/python2.7/pyarena.h
datuma.egg-info/include/python2.7/pycapsule.h
datuma.egg-info/include/python2.7/pyconfig.h
datuma.egg-info/include/python2.7/pyctype.h
datuma.egg-info/include/python2.7/pydebug.h
datuma.egg-info/include/python2.7/pyerrors.h
datuma.egg-info/include/python2.7/pyexpat.h
datuma.egg-info/include/python2.7/pyfpe.h
datuma.egg-info/include/python2.7/pygetopt.h
datuma.egg-info/include/python2.7/pymacconfig.h
datuma.egg-info/include/python2.7/pymactoolbox.h
datuma.egg-info/include/python2.7/pymath.h
datuma.egg-info/include/python2.7/pymem.h
datuma.egg-info/include/python2.7/pyport.h
datuma.egg-info/include/python2.7/pystate.h
datuma.egg-info/include/python2.7/pystrcmp.h
datuma.egg-info/include/python2.7/pystrtod.h
datuma.egg-info/include/python2.7/pythonrun.h
datuma.egg-info/include/python2.7/pythread.h
datuma.egg-info/include/python2.7/rangeobject.h
datuma.egg-info/include/python2.7/setobject.h
datuma.egg-info/include/python2.7/sliceobject.h
datuma.egg-info/include/python2.7/stringobject.h
datuma.egg-info/include/python2.7/structmember.h
datuma.egg-info/include/python2.7/structseq.h
datuma.egg-info/include/python2.7/symtable.h
datuma.egg-info/include/python2.7/sysmodule.h
datuma.egg-info/include/python2.7/timefuncs.h
datuma.egg-info/include/python2.7/token.h
datuma.egg-info/include/python2.7/traceback.h
datuma.egg-info/include/python2.7/tupleobject.h
datuma.egg-info/include/python2.7/ucnhash.h
datuma.egg-info/include/python2.7/unicodeobject.h
datuma.egg-info/include/python2.7/warnings.h
datuma.egg-info/include/python2.7/weakrefobject.h
datuma.egg-info/lib/python2.7/UserDict.py
datuma.egg-info/lib/python2.7/UserDict.pyc
datuma.egg-info/lib/python2.7/_abcoll.py
datuma.egg-info/lib/python2.7/_abcoll.pyc
datuma.egg-info/lib/python2.7/_weakrefset.py
datuma.egg-info/lib/python2.7/_weakrefset.pyc
datuma.egg-info/lib/python2.7/abc.py
datuma.egg-info/lib/python2.7/abc.pyc
datuma.egg-info/lib/python2.7/codecs.py
datuma.egg-info/lib/python2.7/codecs.pyc
datuma.egg-info/lib/python2.7/copy_reg.py
datuma.egg-info/lib/python2.7/copy_reg.pyc
datuma.egg-info/lib/python2.7/fnmatch.py
datuma.egg-info/lib/python2.7/fnmatch.pyc
datuma.egg-info/lib/python2.7/genericpath.py
datuma.egg-info/lib/python2.7/genericpath.pyc
datuma.egg-info/lib/python2.7/linecache.py
datuma.egg-info/lib/python2.7/linecache.pyc
datuma.egg-info/lib/python2.7/locale.py
datuma.egg-info/lib/python2.7/locale.pyc
datuma.egg-info/lib/python2.7/no-global-site-packages.txt
datuma.egg-info/lib/python2.7/ntpath.py
datuma.egg-info/lib/python2.7/orig-prefix.txt
datuma.egg-info/lib/python2.7/os.py
datuma.egg-info/lib/python2.7/os.pyc
datuma.egg-info/lib/python2.7/posixpath.py
datuma.egg-info/lib/python2.7/posixpath.pyc
datuma.egg-info/lib/python2.7/re.py
datuma.egg-info/lib/python2.7/re.pyc
datuma.egg-info/lib/python2.7/site.py
datuma.egg-info/lib/python2.7/site.pyc
datuma.egg-info/lib/python2.7/sre.py
datuma.egg-info/lib/python2.7/sre_compile.py
