Metadata-Version: 1.1
Name: datuma
Version: 0.4.dev0
Summary: A Tool to migrate data between database instances with JSON configuration files.
Home-page: https://github.com/ndrive/datuma
Author: André Freitas
Author-email: andre.freitas@ndrive.com
License: MIT
Platform: UNKNOWN
Classifier: Development Status :: 3 - Alpha
Classifier: Intended Audience :: Developers
Classifier: Topic :: Software Development :: Build Tools
Classifier: License :: OSI Approved :: MIT License
Classifier: Programming Language :: Python :: 3.5
